[
    {"model": "core.Project", "pk": 1, "fields": {"name": "Shoal Creek", "land_owner": "Clarke-McNary", "measusrement_system": "english"}},
    {"model": "core.Project", "pk": 2, "fields": {"name": "Grey Towers", "land_owner": "Gifford Pinchot", "measusrement_system": "ENG"}},
    {"model": "core.Project", "pk": 3, "fields": {"name": "Biltmore", "land_owner": "George Vanderbilt", "measusrement_system": "ENG"}},
    {"model": "core.Project", "pk": 4, "fields": {"name": "Apalachicola Northern Rail", "land_owner": "Edward Ball", "measusrement_system": "ENG"}}
]